MANIFEST.in
README.md
VERSION.txt
setup.cfg
setup.py
src/gitlab_ci_generator.egg-info/PKG-INFO
src/gitlab_ci_generator.egg-info/SOURCES.txt
src/gitlab_ci_generator.egg-info/dependency_links.txt
src/gitlab_ci_generator.egg-info/entry_points.txt
src/gitlab_ci_generator.egg-info/requires.txt
src/gitlab_ci_generator.egg-info/top_level.txt
src/gitlab_ci_generator_package/__init__.py
src/gitlab_ci_generator_package/gitlab_ci_generator.py
src/gitlab_ci_generator_package/templates/gitlab-template.jinja