Metadata-Version: 2.4
Name: gitlab-ci-generator
Version: 1.0.13
Summary: Generates a mono-repo ci file.
Home-page: https://gitlab.com/gary.schaetz/public/gitlab-ci-generator
Author: Gary Schaetz
Author-email: gary@schaetzkc.com
License: MIT
Keywords: gitlab,template,generator,gitlab-ci.yml,dynamic,pipeline
Requires-Dist: jinja2==3.1.2
Requires-Dist: pyaml==21.10.1
Dynamic: author
Dynamic: author-email
Dynamic: description
Dynamic: description-content-type
Dynamic: home-page
Dynamic: keywords
Dynamic: license
Dynamic: requires-dist
Dynamic: summary
